archive/setup.py
esp_8266_micropython/__init__.py
esp_8266_micropython/esp_8266_max.py
esp_8266_micropython/esp_8266_min.py
esp_8266_micropython/main.py
s3_extend/__init__.py
s3_extend/s32.py
s3_extend/s3a.py
s3_extend/s3c.py
s3_extend/s3e.py
s3_extend/s3p.py
s3_extend/s3r.py
s3_extend/s3rh.py
s3_extend/s3rp.py
s3_extend/gateways/__init__.py
s3_extend/gateways/arduino_gateway.py
s3_extend/gateways/cpx_gateway.py
s3_extend/gateways/esp32_gateway.py
s3_extend/gateways/esp8266_gateway.py
s3_extend/gateways/picoboard_gateway.py
s3_extend/gateways/robohat_gateway.py
s3_extend/gateways/rpi_gateway.py
s3_extend/gateways/rpi_pico_gateway.py
s3_extend/gateways/servo.py
s3_extend/gateways/sonar.py
s3_extend/gateways/stepper.py
s3_extend/gateways/ws_gateway.py
s3_extend-1.35.dist-info/licenses/LICENSE
s3_extend-1.35.dist-info/METADATA
s3_extend-1.35.dist-info/WHEEL
s3_extend-1.35.dist-info/entry_points.txt
s3_extend-1.35.dist-info/top_level.txt
s3_extend-1.35.dist-info/RECORD
