Metadata-Version: 2.4
Name: s3-extend
Version: 1.35
Summary: Scratch3 Extension Servers
Author-email: Alan Yorinks <MisterYsLab@gmail.com>
License: AGPL-3.0-or-later
Keywords: Scratch, Extensions,Python
Classifier: Development Status :: 5 - Production/Stable
Classifier: Environment :: Other Environment
Classifier: Intended Audience :: Developers
Classifier: Intended Audience :: Education
Classifier: Operating System :: OS Independent
Classifier: Topic :: Software Development :: Libraries :: Python Modules
Requires-Python: >=3.8
License-File: LICENSE
Requires-Dist: python-banyan>=3.10
Requires-Dist: pymata-express>=1.11
Requires-Dist: pymata-rh
Requires-Dist: pymata-cpx
Requires-Dist: tmx-pico-aio
Requires-Dist: telemetrix-aio>=1.8
Requires-Dist: telemetrix-esp32
Dynamic: license-file
